googletrans/__init__.py
googletrans/client.py
googletrans/constants.py
googletrans/gtoken.py
googletrans/models.py
googletrans/urls.py
googletrans/utils.py
py_googletrans-4.0.0.dist-info/LICENSE
py_googletrans-4.0.0.dist-info/METADATA
py_googletrans-4.0.0.dist-info/WHEEL
py_googletrans-4.0.0.dist-info/entry_points.txt
py_googletrans-4.0.0.dist-info/top_level.txt
py_googletrans-4.0.0.dist-info/RECORD
